neo4j_gds/__init__.py
neo4j_gds/algorithms/__init__.py
neo4j_gds/algorithms/algorithm.py
neo4j_gds/algorithms/rank.py
neo4j_gds/algorithms/rank_configuration.py
neo4j_gds/collection.py
neo4j_gds/exceptions.py
neo4j_gds/projection.py
neo4j_gds/queries/__init__.py
neo4j_gds/queries/basic.py
neo4j_gds/query.py
neo4j_gds/tests/__init__.py
neo4j_gds/tests/config.py
neo4j_gds/tests/conftest.py
neo4j_gds/tests/test_projection.py
neo4j_gds/tests/test_rank.py
neo4j_gds/utils.py
neo4j_gds-0.1.1.dist-info/WHEEL
neo4j_gds-0.1.1.dist-info/METADATA
neo4j_gds-0.1.1.dist-info/RECORD
