Metadata-Version: 2.1
Name: neo4j-gds
Version: 0.1.1
Summary: Library to build neo4j's queries with special attention on Graph Data Science library calls
License: MIT
Author: Pablo Cabezas
Author-email: pabcabsal@gmail.com
Requires-Python: >=3.8,<4.0
Classifier: License :: OSI Approved :: MIT License
Classifier: Programming Language :: Python :: 3
Classifier: Programming Language :: Python :: 3.8
Requires-Dist: py2neo (>=5.0b5,<6.0)
